[{"id":"439793301554462721","system":null,"locale":null,"flags":null,"username":"iDarkLightning","bot":false,"discriminator":"3514","avatar":"e32da2f7a5cdb3ca29c5efe93aa3919f","lastMessageChannelID":null,"createdTimestamp":1524925294055,"defaultAvatarURL":"https://cdn.discordapp.com/embed/avatars/4.png","tag":"iDarkLightning#3514","avatarURL":"https://cdn.discordapp.com/avatars/439793301554462721/e32da2f7a5cdb3ca29c5efe93aa3919f.webp","displayAvatarURL":"https://cdn.discordapp.com/avatars/439793301554462721/e32da2f7a5cdb3ca29c5efe93aa3919f.webp"},{"id":"184811596986449921","system":null,"locale":null,"flags":128,"username":"owen","bot":false,"discriminator":"3242","avatar":"e4ce15c49c437be01eaec0b03a075131","lastMessageChannelID":null,"createdTimestamp":1464132918355,"defaultAvatarURL":"https://cdn.discordapp.com/embed/avatars/2.png","tag":"owen#3242","avatarURL":"https://cdn.discordapp.com/avatars/184811596986449921/e4ce15c49c437be01eaec0b03a075131.webp","displayAvatarURL":"https://cdn.discordapp.com/avatars/184811596986449921/e4ce15c49c437be01eaec0b03a075131.webp"},{"id":"601051988485996544","system":null,"locale":null,"flags":128,"username":"Rybot666","bot":false,"discriminator":"5334","avatar":"63b47c5ed85f781398a31d67e3688c40","lastMessageChannelID":null,"createdTimestamp":1563372361061,"defaultAvatarURL":"https://cdn.discordapp.com/embed/avatars/4.png","tag":"Rybot666#5334","avatarURL":"https://cdn.discordapp.com/avatars/601051988485996544/63b47c5ed85f781398a31d67e3688c40.webp","displayAvatarURL":"https://cdn.discordapp.com/avatars/601051988485996544/63b47c5ed85f781398a31d67e3688c40.webp"},{"id":"604605371453145091","system":null,"locale":null,"flags":null,"username":"NiceGarytheGoat","bot":false,"discriminator":"1295","avatar":null,"lastMessageChannelID":null,"createdTimestamp":1564219553579,"defaultAvatarURL":"https://cdn.discordapp.com/embed/avatars/0.png","tag":"NiceGarytheGoat#1295","avatarURL":null,"displayAvatarURL":"https://cdn.discordapp.com/embed/avatars/0.png"},{"id":"451834483034030102","system":null,"locale":null,"flags":null,"username":"Psychopomp**","bot":false,"discriminator":"8799","avatar":"9e3608d34f7d0741c2f046e600576cfd","lastMessageChannelID":null,"createdTimestamp":1527796135434,"defaultAvatarURL":"https://cdn.discordapp.com/embed/avatars/4.png","tag":"Psychopomp**#8799","avatarURL":"https://cdn.discordapp.com/avatars/451834483034030102/9e3608d34f7d0741c2f046e600576cfd.webp","displayAvatarURL":"https://cdn.discordapp.com/avatars/451834483034030102/9e3608d34f7d0741c2f046e600576cfd.webp"},{"id":"327824770160918528","system":null,"locale":null,"flags":128,"username":"Boris NL","bot":false,"discriminator":"1500","avatar":"19503ac0f7e8d7a72b0d964187658be3","lastMessageChannelID":null,"createdTimestamp":1498229915896,"defaultAvatarURL":"https://cdn.discordapp.com/embed/avatars/0.png","tag":"Boris NL#1500","avatarURL":"https://cdn.discordapp.com/avatars/327824770160918528/19503ac0f7e8d7a72b0d964187658be3.webp","displayAvatarURL":"https://cdn.discordapp.com/avatars/327824770160918528/19503ac0f7e8d7a72b0d964187658be3.webp"},{"id":"305245974572302346","system":null,"locale":null,"flags":null,"username":"Feski713","bot":false,"discriminator":"6662","avatar":"e1578101b16ecbf7ee46895d70e9bef8","lastMessageChannelID":null,"createdTimestamp":1492846711534,"defaultAvatarURL":"https://cdn.discordapp.com/embed/avatars/2.png","tag":"Feski713#6662","avatarURL":"https://cdn.discordapp.com/avatars/305245974572302346/e1578101b16ecbf7ee46895d70e9bef8.webp","displayAvatarURL":"https://cdn.discordapp.com/avatars/305245974572302346/e1578101b16ecbf7ee46895d70e9bef8.webp"},{"id":"727488503373365299","system":null,"locale":null,"flags":null,"username":"luki2005st","bot":false,"discriminator":"1301","avatar":null,"lastMessageChannelID":null,"createdTimestamp":1593517175287,"defaultAvatarURL":"https://cdn.discordapp.com/embed/avatars/1.png","tag":"luki2005st#1301","avatarURL":null,"displayAvatarURL":"https://cdn.discordapp.com/embed/avatars/1.png"},{"id":"128824026977140736","system":null,"locale":null,"flags":null,"username":"Friendlyguy","bot":false,"discriminator":"3543","avatar":"6ec73f2d04ba3839d8bf96e62362efd7","lastMessageChannelID":null,"createdTimestamp":1450784441466,"defaultAvatarURL":"https://cdn.discordapp.com/embed/avatars/3.png","tag":"Friendlyguy#3543","avatarURL":"https://cdn.discordapp.com/avatars/128824026977140736/6ec73f2d04ba3839d8bf96e62362efd7.webp","displayAvatarURL":"https://cdn.discordapp.com/avatars/128824026977140736/6ec73f2d04ba3839d8bf96e62362efd7.webp"},{"id":"183673450114711552","system":null,"locale":null,"flags":null,"username":"Artwo","bot":false,"discriminator":"6628","avatar":"6217218a7f48d68b0b95fb559dccd370","lastMessageChannelID":null,"createdTimestamp":1463861562995,"defaultAvatarURL":"https://cdn.discordapp.com/embed/avatars/3.png","tag":"Artwo#6628","avatarURL":"https://cdn.discordapp.com/avatars/183673450114711552/6217218a7f48d68b0b95fb559dccd370.webp","displayAvatarURL":"https://cdn.discordapp.com/avatars/183673450114711552/6217218a7f48d68b0b95fb559dccd370.webp"},{"id":"455919382946906124","system":null,"locale":null,"flags":null,"username":"heinzkopf77","bot":false,"discriminator":"9202","avatar":"cbe99ed9b55d384f4dd54c6667a99d0d","lastMessageChannelID":null,"createdTimestamp":1528770051467,"defaultAvatarURL":"https://cdn.discordapp.com/embed/avatars/2.png","tag":"heinzkopf77#9202","avatarURL":"https://cdn.discordapp.com/avatars/455919382946906124/cbe99ed9b55d384f4dd54c6667a99d0d.webp","displayAvatarURL":"https://cdn.discordapp.com/avatars/455919382946906124/cbe99ed9b55d384f4dd54c6667a99d0d.webp"},{"id":"464863856431464450","system":null,"locale":null,"flags":null,"username":"GaRLicBrEd","bot":false,"discriminator":"9457","avatar":"ce67a0b8546d93fdcdf2c7c1d8523527","lastMessageChannelID":null,"createdTimestamp":1530902580126,"defaultAvatarURL":"https://cdn.discordapp.com/embed/avatars/2.png","tag":"GaRLicBrEd#9457","avatarURL":"https://cdn.discordapp.com/avatars/464863856431464450/ce67a0b8546d93fdcdf2c7c1d8523527.webp","displayAvatarURL":"https://cdn.discordapp.com/avatars/464863856431464450/ce67a0b8546d93fdcdf2c7c1d8523527.webp"},{"id":"303938986576052225","system":null,"locale":null,"flags":128,"username":"famferenc","bot":false,"discriminator":"8673","avatar":"deaa12f093c8eabcc69ce09cd2fddbb3","lastMessageChannelID":null,"createdTimestamp":1492535101313,"defaultAvatarURL":"https://cdn.discordapp.com/embed/avatars/3.png","tag":"famferenc#8673","avatarURL":"https://cdn.discordapp.com/avatars/303938986576052225/deaa12f093c8eabcc69ce09cd2fddbb3.webp","displayAvatarURL":"https://cdn.discordapp.com/avatars/303938986576052225/deaa12f093c8eabcc69ce09cd2fddbb3.webp"},{"id":"150124453815255040","system":null,"locale":null,"flags":null,"username":"Reggie Belafonte","bot":false,"discriminator":"4867","avatar":"9ccb997ba5708bed53859772cee1e81f","lastMessageChannelID":null,"createdTimestamp":1455862858967,"defaultAvatarURL":"https://cdn.discordapp.com/embed/avatars/2.png","tag":"Reggie Belafonte#4867","avatarURL":"https://cdn.discordapp.com/avatars/150124453815255040/9ccb997ba5708bed53859772cee1e81f.webp","displayAvatarURL":"https://cdn.discordapp.com/avatars/150124453815255040/9ccb997ba5708bed53859772cee1e81f.webp"}]